MANIFEST.in
README.md
setup.py
bin/habitica
habitica/__init__.py
habitica/api.py
habitica/core.py
habitica.egg-info/PKG-INFO
habitica.egg-info/SOURCES.txt
habitica.egg-info/dependency_links.txt
habitica.egg-info/pbr.json
habitica.egg-info/requires.txt
habitica.egg-info/top_level.txt