Metadata-Version: 1.0
Name: habitica
Version: 0.0.13
Summary: Commandline interface to Habitica (http://habitica.com)
Home-page: https://github.com/philadams/habitica
Author: Phil Adams
Author-email: philadams.net@gmail.com
License: LICENSE.txt
Platform: UNKNOWN
